{
  "home": {
    "header": {
      "logo": {
        "title": "OrganiCo",
        "link": "/"
      },
      "nav": {
        "links": [
          { "text": "Home", "href": "/" },
          { "text": "About", "href": "/about" },
          { "text": "Shop", "href": "/shop" },
          { "text": "Blog", "href": "/blog" },
          { "text": "Contact", "href": "/contact" }
        ]
      }
    },
    "banner": {
      "image": {
        "src": "https://github.com/y1tkyy/organic-fashion/blob/main/src/assets/images/banner.png?raw=true",
        "alt": "Banner Image"
      },
      "title": "Fresh Flowers, Naturally",
      "paragraph": "At OrganiCo, we believe in the beauty of nature. Our flowers are handpicked from organic farms to bring you the freshest blooms, sustainably grown to brighten your day. Whether you’re decorating your home or celebrating a special occasion, we have something for every moment.",
      "button": "Shop now"
    },
    "categorySelection": {
      "title": "Shop By Categories",
      "breakImg": {
        "src": "https://github.com/y1tkyy/organic-fashion/blob/main/src/assets/images/category5.png?raw=true",
        "alt": "Break Image"
      },
      "categories": [
        {
          "href": "/category1",
          "src": "https://github.com/y1tkyy/organic-fashion/blob/main/src/assets/images/category1.png?raw=true",
          "alt": "Category 1"
        },
        {
          "href": "/category2",
          "src": "https://github.com/y1tkyy/organic-fashion/blob/main/src/assets/images/category2.png?raw=true",
          "alt": "Category 2"
        },
        {
          "href": "/category3",
          "src": "https://github.com/y1tkyy/organic-fashion/blob/main/src/assets/images/category3.png?raw=true",
          "alt": "Category 3"
        },
        {
          "href": "/category4",
          "src": "https://github.com/y1tkyy/organic-fashion/blob/main/src/assets/images/category4.png?raw=true",
          "alt": "Category 4"
        }
      ]
    },
    "newCollection": {
      "title": "New Collection",
      "collections": [
        {
          "href": "/collection1",
          "src": "https://github.com/y1tkyy/organic-fashion/blob/main/src/assets/images/collection1.png?raw=true",
          "alt": "Collection 1"
        },
        {
          "href": "/collection2",
          "src": "https://github.com/y1tkyy/organic-fashion/blob/main/src/assets/images/collection2.png?raw=true",
          "alt": "Collection 2"
        },
        {
          "href": "/collection3",
          "src": "https://github.com/y1tkyy/organic-fashion/blob/main/src/assets/images/collection3.png?raw=true",
          "alt": "Collection 3"
        }
      ],
      "paragraph": "Discover our newest floral creations, designed to complement your lifestyle. From vibrant bouquets to serene indoor plants, our new collection brings nature's finest offerings straight to your doorstep."
    },
    "aboutUs": {
      "image": {
        "src": "https://github.com/y1tkyy/organic-fashion/blob/main/src/assets/images/aboutus.png?raw=true",
        "alt": "About Us Image"
      },
      "title": "About Us",
      "paragraph": {
        "first": "At OrganiCo, we’re passionate about flowers. Our mission is to offer only the highest quality, organic blooms that support sustainable farming practices. We believe in bringing joy and beauty into the lives of our customers while caring for the environment.",
        "second": "Our team works tirelessly to ensure each bouquet is crafted with care, and every stem is ethically sourced. From garden favorites to exotic varieties, our flowers are perfect for any occasion—whether it's a gift, an event, or just to brighten your day."
      },
      "button": "Learn More"
    },
    "footer": {
      "title": "Follow Us",
      "inputsPlc": {
        "name": "Enter your name",
        "email": "Enter a valid email address",
        "message": "Enter your message"
      },
      "image": {
        "src": "https://github.com/y1tkyy/organic-fashion/blob/main/src/assets/images/footer.png?raw=true",
        "alt": "Footer image"
      }
    }
  }
}
